legal_expand/__init__.py
legal_expand/config.py
legal_expand/types.py
legal_expand/core/__init__.py
legal_expand/core/engine.py
legal_expand/core/matcher.py
legal_expand/core/normalizer.py
legal_expand/data/__init__.py
legal_expand/data/dictionary.json
legal_expand/formatters/__init__.py
legal_expand/formatters/base.py
legal_expand/formatters/html.py
legal_expand/formatters/plain_text.py
legal_expand/formatters/structured.py
legal_expand-1.0.0.dist-info/licenses/LICENSE
legal_expand-1.0.0.dist-info/METADATA
legal_expand-1.0.0.dist-info/WHEEL
legal_expand-1.0.0.dist-info/top_level.txt
legal_expand-1.0.0.dist-info/RECORD
