Metadata-Version: 2.4
Name: legal-expand
Version: 1.0.0
Summary: Smart expansion of Spanish legal acronyms. 646 verified acronyms from RAE, BOE and DPEJ. | Expansión inteligente de siglas legales españolas.
Author: 686f6c61
Maintainer: 686f6c61
License: MIT
Project-URL: Homepage, https://github.com/686f6c61/pypi-legal-expand
Project-URL: Documentation, https://github.com/686f6c61/pypi-legal-expand#readme
Project-URL: Repository, https://github.com/686f6c61/pypi-legal-expand
Project-URL: Issues, https://github.com/686f6c61/pypi-legal-expand/issues
Keywords: legal,siglas,acronimos,abreviaturas,español,derecho,legislacion,spanish,law,acronyms,nlp
Classifier: Development Status :: 5 - Production/Stable
Classifier: Intended Audience :: Developers
Classifier: Intended Audience :: Legal Industry
Classifier: License :: OSI Approved :: MIT License
Classifier: Operating System :: OS Independent
Classifier: Programming Language :: Python :: 3
Classifier: Programming Language :: Python :: 3.9
Classifier: Programming Language :: Python :: 3.10
Classifier: Programming Language :: Python :: 3.11
Classifier: Programming Language :: Python :: 3.12
Classifier: Programming Language :: Python :: 3.13
Classifier: Topic :: Text Processing
Classifier: Topic :: Text Processing :: Linguistic
Classifier: Typing :: Typed
Classifier: Natural Language :: Spanish
Requires-Python: >=3.9
License-File: LICENSE
Provides-Extra: dev
Requires-Dist: pytest>=7.0.0; extra == "dev"
Requires-Dist: pytest-cov>=4.0.0; extra == "dev"
Dynamic: license-file
